mimic_utils/__init__.py
mimic_utils/__main__.py
mimic_utils/_version.py
mimic_utils/transpile.py
mimic_utils/sqlglot/__init__.py
mimic_utils/sqlglot/bigquery.py
mimic_utils/sqlglot/duckdb.py
mimic_utils/sqlglot/postgres.py
mimic_utils-1.0.0.dist-info/METADATA
mimic_utils-1.0.0.dist-info/WHEEL
mimic_utils-1.0.0.dist-info/entry_points.txt
mimic_utils-1.0.0.dist-info/licenses/LICENSE
mimic_utils-1.0.0.dist-info/RECORD
