Metadata-Version: 2.1
Name: mimic_utils
Version: 1.0.0
Summary: Utilities to support building and analyzing the MIMIC database(s)
Project-URL: Homepage, https://github.com/MIT-LCP/mimic-code
Project-URL: Bug Tracker, https://github.com/MIT-LCP/mimic-code/issues
Author-email: Alistair Johnson <aewj@mit.edu>
License: MIT License
License-File: LICENSE
Classifier: License :: OSI Approved :: Apache Software License
Classifier: Operating System :: OS Independent
Classifier: Programming Language :: Python :: 3
Requires-Python: >=3.8
Requires-Dist: numpy
Requires-Dist: pandas
Requires-Dist: sqlglot
